pyngo/.DS_Store
pyngo/README.md
pyngo/manage.py
pyngo/pyngo/__init__.py
pyngo/pyngo/asgi.py
pyngo/pyngo/settings.py
pyngo/pyngo/urls.py
pyngo/pyngo/wsgi.py
pyngo/sreality/.DS_Store
pyngo/sreality/__init__.py
pyngo/sreality/admin.py
pyngo/sreality/apps.py
pyngo/sreality/migrations/0001_initial.py
pyngo/sreality/migrations/__init__.py
pyngo/sreality/models.py
pyngo/sreality/templates/sreality.html
pyngo/sreality/tests.py
pyngo/sreality/urls.py
pyngo/sreality/views.py
pydjango-0.1.8.dist-info/METADATA
pydjango-0.1.8.dist-info/WHEEL
pydjango-0.1.8.dist-info/RECORD
