Metadata-Version: 2.1
Name: pydjango
Version: 0.1.8
Summary: 
Author: Roman Hartig
Author-email: roman.hartig@gmail.com
Requires-Python: >=3.10,<4.0
Classifier: Programming Language :: Python :: 3
Classifier: Programming Language :: Python :: 3.10
Classifier: Programming Language :: Python :: 3.11
Requires-Dist: django (>=4.1.7,<5.0.0)
